trickery/__init__.py
trickery/listener.py
trickery/target.py
trickery-1.0.1.dist-info/LICENSE.txt
trickery-1.0.1.dist-info/METADATA
trickery-1.0.1.dist-info/WHEEL
trickery-1.0.1.dist-info/top_level.txt
trickery-1.0.1.dist-info/RECORD
