Metadata-Version: 2.1
Name: trickery
Version: 1.0.1
Summary: To bind a third-party service into a custom code.
Home-page: https://socioware1.github.io/trickery/index.html
Author: UNKNOWN
Author-email: UNKNOWN
License: MIT
Download-URL: https://github.com/socioware1/trickery/blob/main/archive/trickery.rar
Keywords: Pentesting,Reverse-Engineering,Backdoor,CyberSecurity
Platform: UNKNOWN
Classifier: Development Status :: 4 - Beta
Classifier: Intended Audience :: Developers
Classifier: Topic :: Software Development :: Build Tools
Classifier: License :: OSI Approved :: MIT License
Classifier: Programming Language :: Python :: 3
Classifier: Programming Language :: Python :: 3.4
Classifier: Programming Language :: Python :: 3.5
Classifier: Programming Language :: Python :: 3.6
Classifier: Programming Language :: Python :: 3.7
Classifier: Programming Language :: Python :: 3.8
